<?xml version="1.0" encoding="UTF-8"?>
<help xmlns:help="http://code.google.com/p/helpgenerator/">
	<head>
		<name>Aurora</name>
		<icon href="AppIcon32.png"/>
		<website href="http://metaquark.de/"/>
		<AppleTitle>Aurora Help</AppleTitle>
	</head>
	<access>
		<main>
			<item href="discover">Learn how to use Aurora to wake up listening to your favorite music.</item>
			<item href="problems">Trouble? Check here for answers.</item>
		</main>
		<featured>
			<item href="playlists"/>
		</featured>
	</access>
	<pages>
		<page>
			<tag>discover</tag>
			<title>Discover Aurora</title>
			<content><b>Aurora</b> is a <help:a href="problems">great</help:a> application! <img src="../gfx/AppIcon32.png"/></content>
		</page>
		<page>
			<tag>problems</tag>
			<tag>x_wake</tag>
			<title>Solving Problems</title>
			<content>
				No problems.
			</content>
		</page>
		<page>
			<tag>playlists</tag>
			<title>How Aurora handles Playlists</title>
			<content>
				No way.
			</content>
		</page>
	</pages>
	<index>
		<item tag="x_wake">waking up</item>
	</index>
</help>
